{
    "has_precipitation":  false,
    "temperature":  0.5,
    "downfall":  0.5,
    "effects":  {
                    "sky_color":  9437439,
                    "fog_color":  7864319,
                    "water_color":  8388863,
                    "water_fog_color":  8388863,
                    "mood_sound":  {
                                       "sound":  "minecraft:ambient.cave",
                                       "tick_delay":  6000,
                                       "block_search_extent":  8,
                                       "offset":  2.0
                                   },
                    "music":  {
                                  "sound":  "minecraft:music.overworld.meadow",
                                  "min_delay":  12000,
                                  "max_delay":  24000,
                                  "replace_current_music":  false
                              }
                },
    "spawners":  {
                     "monster":  [

                                 ],
                     "creature":  [

                                  ],
                     "ambient":  [

                                 ],
                     "water_creature":  [

                                        ],
                     "water_ambient":  [

                                       ],
                     "misc":  [

                              ]
                 },
    "spawn_costs":  {

                    },
    "carvers":  {
                    "air":  [

                            ]
                },
    "features":  [

                 ]
}
